gravpy/__init__.py
gravpy/general.py
gravpy/gravpy.py
gravpy/interferometers.py
gravpy/noise.py
gravpy/plotting.py
gravpy/pulsar_data.txt
gravpy/pulsar_list.txt
gravpy/sources.py
gravpy/timingarray.py
gravpy/data/ETD-psd.txt
gravpy/data/IPTA-pulsars.dat
gravpy/data/__init__.py
gravpy/data/aligo_freqVector.txt
gravpy/data/aplus-asd.dat
gravpy/data/atnf.dat
gravpy/data/atnf.py
gravpy/data/et-d-curve.txt
gravpy/data/o1_data50Mpc_step1.txt
gravpy/data/__pycache__/__init__.cpython-37.pyc
gravpy/data/__pycache__/atnf.cpython-37.pyc
gravpy-0.2.4.dist-info/AUTHORS.rst
gravpy-0.2.4.dist-info/LICENSE
gravpy-0.2.4.dist-info/METADATA
gravpy-0.2.4.dist-info/WHEEL
gravpy-0.2.4.dist-info/top_level.txt
gravpy-0.2.4.dist-info/RECORD
