Metadata-Version: 2.1
Name: gravpy
Version: 0.2.4
Summary: A sandbox for gravitational wave astronomy.
Home-page: https://github.com/transientlunatic/grasshopper
Author: Daniel Williams
Author-email: daniel.williams@glasgow.ac.uk
License: ISCL
Keywords: gravpy
Platform: UNKNOWN
Classifier: Development Status :: 2 - Pre-Alpha
Classifier: Intended Audience :: Developers
Classifier: License :: OSI Approved :: ISC License (ISCL)
Classifier: Natural Language :: English
Classifier: Programming Language :: Python :: 2
Classifier: Programming Language :: Python :: 2.6
Classifier: Programming Language :: Python :: 2.7
Classifier: Programming Language :: Python :: 3
Classifier: Programming Language :: Python :: 3.3
Classifier: Programming Language :: Python :: 3.4
Classifier: Programming Language :: Python :: 3.5
Requires-Dist: numpy
Requires-Dist: scipy
Requires-Dist: matplotlib (>1.5)
Requires-Dist: astropy
